rsp/__init__.py
rsp/common/__init__.py
rsp/common/color/__init__.py
rsp/common/color/color.py
rsp/common/console/__init__.py
rsp/common/console/console.py
rsp/common/download/__init__.py
rsp/common/download/download.py
rsp/common/drawing/__init__.py
rsp/common/drawing/drawing.py
rsp_common-0.0.34.dist-info/LICENSE
rsp_common-0.0.34.dist-info/METADATA
rsp_common-0.0.34.dist-info/WHEEL
rsp_common-0.0.34.dist-info/top_level.txt
rsp_common-0.0.34.dist-info/RECORD
