Metadata-Version: 2.1
Name: rsp-common
Version: 0.0.34
Summary: Some basic functionalities
Home-page: https://github.com/SchulzR97/rsp-common
Author: Robert Schulz
Author-email: schulzr256@gmail.com
License: MIT
Keywords: python,OpenCV,UI,UserInterface,Frontend
Classifier: Development Status :: 3 - Alpha
Classifier: Intended Audience :: Education
Classifier: Programming Language :: Python :: 2
Classifier: Programming Language :: Python :: 3
Classifier: Operating System :: MacOS :: MacOS X
Classifier: Operating System :: Microsoft :: Windows
Classifier: Operating System :: POSIX :: Linux
License-File: LICENSE
